gcloud_changer/__init__.py
gcloud_changer/gcloud_set_account.py
gcloud_account_changer-0.1.dist-info/METADATA
gcloud_account_changer-0.1.dist-info/WHEEL
gcloud_account_changer-0.1.dist-info/entry_points.txt
gcloud_account_changer-0.1.dist-info/top_level.txt
gcloud_account_changer-0.1.dist-info/RECORD
