Metadata-Version: 2.4
Name: gcloud-account-changer
Version: 0.1
Summary: Google Cloud CLI Account & Project Selector
Author-email: Lee Ji-Ho <search5@gmail.com>
Project-URL: Homepage, https://github.com/search5/gcloud-account-changer
Keywords: gcp,gcloud
Classifier: Programming Language :: Python
Classifier: Operating System :: POSIX :: Linux
Classifier: Topic :: Internet :: WWW/HTTP
Classifier: Topic :: Software Development :: Build Tools
Requires-Python: >=3.8
Requires-Dist: urwid
